toolshop/__init__.py
toolshop/agent/__init__.py
toolshop/agent/agent.py
toolshop/agent/instructions.py
toolshop/cli/cli.py
toolshop/core/base.py
toolshop/core/logging.py
toolshop/core/meta.py
toolshop/tools/data.py
toolshop/tools/file.py
toolshop/tools/gcp.py
toolshop/tools/misc.py
toolshop/tools/terminal.py
toolshop-0.1.4.dist-info/METADATA
toolshop-0.1.4.dist-info/WHEEL
toolshop-0.1.4.dist-info/entry_points.txt
toolshop-0.1.4.dist-info/RECORD
