Metadata-Version: 2.1
Name: toolshop
Version: 0.1.4
Summary: A Tool Framework for AI Agents
Author: Andrew Hannigan
Author-email: Andrew.S.Hannigan@Gmail.com
Requires-Python: >=3.9,<3.13
Classifier: Programming Language :: Python :: 3
Classifier: Programming Language :: Python :: 3.9
Classifier: Programming Language :: Python :: 3.10
Classifier: Programming Language :: Python :: 3.11
Classifier: Programming Language :: Python :: 3.12
Requires-Dist: ascii-graph (>=1.5.1,<2.0.0)
Requires-Dist: click (>=8.1.7,<9.0.0)
Requires-Dist: google-cloud-bigquery-storage (>=2.25.0,<3.0.0)
Requires-Dist: httpx (>=0.27.0,<0.28.0)
Requires-Dist: marvin (>=2.3.6,<3.0.0)
Requires-Dist: sqlalchemy (>=2.0.29,<3.0.0)
Requires-Dist: sqlalchemy-bigquery (>=1.11.0,<2.0.0)
